clerk_timestamp.py
josephhaaga_clerk_timestamp-0.0.3.dist-info/METADATA
josephhaaga_clerk_timestamp-0.0.3.dist-info/WHEEL
josephhaaga_clerk_timestamp-0.0.3.dist-info/entry_points.txt
josephhaaga_clerk_timestamp-0.0.3.dist-info/top_level.txt
josephhaaga_clerk_timestamp-0.0.3.dist-info/RECORD
