Metadata-Version: 2.1
Name: josephhaaga-clerk-timestamp
Version: 0.0.3
Summary: Appends timestamps to your clerk journal entries
Home-page: https://github.com/josephhaaga/clerk-timestamp
Author: Joseph Haaga
Author-email: haaga.joe@gmail.com
License: UNKNOWN
Project-URL: Bug Tracker, https://github.com/josephhaaga/clerk-timestamp/issues
Platform: UNKNOWN
Classifier: Programming Language :: Python :: 3
Classifier: License :: OSI Approved :: MIT License
Classifier: Operating System :: OS Independent
Requires-Python: >=3.7
Requires-Dist: josephhaaga-clerk (>=0.0.3)
